vslogging/__init__.py
vslogging/vslogging.py
vslogging-0.1.4.dist-info/METADATA
vslogging-0.1.4.dist-info/WHEEL
vslogging-0.1.4.dist-info/top_level.txt
vslogging-0.1.4.dist-info/RECORD
