Metadata-Version: 2.1
Name: vslogging
Version: 0.1.4
Summary: Very Simple Logging
Home-page: UNKNOWN
Author: Jason Smith
Author-email: UNKNOWN
License: MIT
Platform: UNKNOWN
